colosseum_sdk/__init__.py
colosseum_sdk/colosseum_sdk.py
colosseum_sdk/tests/__init__.py
colosseum_sdk/tests/colosseum_sdk_test.py
colosseum_sdk/tests/fixtures.py
colosseum_sdk/utils.py
colosseum_sdk-0.1.3.dist-info/LICENSE
colosseum_sdk-0.1.3.dist-info/WHEEL
colosseum_sdk-0.1.3.dist-info/METADATA
colosseum_sdk-0.1.3.dist-info/RECORD
